<BakedData type="BoneAnimationTextures" ID="208b4a6142a045fcaceb13a13f06be5d" version="1.0"><Unit system="METRIC" unit="METERS" length="1.0" unit_scale="100.0" unit_invert_x="False" unit_invert_y="True" unit_invert_z="False" unit_invert_v="True" /><Frames sampling="STACK_SINGLE" count="119" padded="119" padding="0" rate="30.0" ref="1" ref_padding="False" /><Mesh path="G:\Unreal Projects\BlenderGameToolsDoc\Source\BAT\PosQuatPacked\Meshes\SM_BakedMesh.BAT.fbx" uv_index="1" bounds_offset_min_x="852.5362548828125" bounds_offset_min_y="971.7843017578125" bounds_offset_min_z="124.73441314697266" bounds_offset_max_x="822.9940185546875" bounds_offset_max_y="1967.74658203125" bounds_offset_max_z="2733.88427734375" /><Textures><Texture type="Skinning" width="4090" height="2" rows="1.0" mode="ROWS" path="G:\Unreal Projects\BlenderGameToolsDoc\Source\BAT\PosQuatPacked\Textures\T_BakedMesh.BAT_Skinning.exr"><Row name="Indices"><R mode="INDEX" index="1" /><G mode="INDEX" index="2" /><B mode="INDEX" index="3" /><A mode="INDEX" index="4" /></Row><Row name="Weights"><R mode="WEIGHT" index="1" /><G mode="WEIGHT" index="2" /><B mode="WEIGHT" index="3" /><A mode="WEIGHT" index="4" /></Row></Texture><Texture type="Animation" width="60" frame_width="1.0" height="122" frame_height="1.0" mode="STACK_SINGLE" path="G:\Unreal Projects\BlenderGameToolsDoc\Source\BAT\PosQuatPacked\Textures\T_BakedMesh.BAT_PosQuatPacked.exr"><R mode="POSITION" axis_order="XYZ" component="X" remapped="False" range_offset="-2087.56591796875" range="3672.55712890625" range_valid="True" /><G mode="POSITION" axis_order="XYZ" component="Y" remapped="False" range_offset="-3374.6142578125" range="7406.5654296875" range_valid="True" /><B mode="POSITION" axis_order="XYZ" component="Z" remapped="False" range_offset="-3638.88818359375" range="10451.1630859375" range_valid="True" /><A mode="ROTATION" axis_order="XYZ" rot_mode="QUAT" quat="XYZW" remapped="False" range_offset="0.0" range="1.0" range_valid="True" /></Texture></Textures><Animations><Animation name="Peewee_Ground_Idle" start_frame="2" end_frame="11" frames="9" /><Animation name="Peewee_Ground_Excited" start_frame="12" end_frame="54" frames="42" /><Animation name="Peewee_Ground_Sad" start_frame="55" end_frame="104" frames="49" /><Animation name="Peewee_Ground_Trot" start_frame="105" end_frame="120" frames="15" /></Animations></BakedData>