<BakedData type="VertexAnimationTextures" ID="c153bc1c327d488a8a8d2181654832ff" version="1.0"><Unit system="METRIC" unit="METERS" length="1.0" unit_scale="100.0" unit_invert_x="False" unit_invert_y="True" unit_invert_z="False" unit_invert_v="True" unit_axis_order="XYZ" /><Frames sampling="STACK_SINGLE" count="60" padded="68" padding="1" rate="30.0" width="1.0" height="1.0" ref="1" /><Mesh path="G:\Unreal Projects\GameTools\Source\VAT\FrameStep\Meshes\SM_Peewee.VAT.fbx" uv_index="1" bounds_offset_min_x="852.5362548828125" bounds_offset_min_y="888.6668701171875" bounds_offset_min_z="124.73441314697266" bounds_offset_max_x="818.7027587890625" bounds_offset_max_y="1967.74658203125" bounds_offset_max_z="2565.58544921875" /><Textures><Texture type="Offset" mode="OFFSET" width="4090" height="68" path="G:\Unreal Projects\GameTools\Source\VAT\FrameStep\Textures\T_Peewee.VAT_Offset.exr" remapped="False" range_x="&lt;bpy_float[3], VATBAKER_PG_Report.tex_offset_range&gt;" range_y="&lt;bpy_float[3], VATBAKER_PG_Report.tex_offset_range&gt;" range_z="&lt;bpy_float[3], VATBAKER_PG_Report.tex_offset_range&gt;" range_offset_x="&lt;bpy_float[3], VATBAKER_PG_Report.tex_offset_range_offset&gt;" range_offset_y="&lt;bpy_float[3], VATBAKER_PG_Report.tex_offset_range_offset&gt;" range_offset_z="&lt;bpy_float[3], VATBAKER_PG_Report.tex_offset_range_offset&gt;" /><Texture type="Normal" width="4090" height="68" path="G:\Unreal Projects\GameTools\Source\VAT\FrameStep\Textures\T_Peewee.VAT_Normal.exr" remapped="True" range_x="&lt;bpy_float[3], VATBAKER_PG_Report.tex_normal_range&gt;" range_y="&lt;bpy_float[3], VATBAKER_PG_Report.tex_normal_range&gt;" range_z="&lt;bpy_float[3], VATBAKER_PG_Report.tex_normal_range&gt;" range_offset_x="&lt;bpy_float[3], VATBAKER_PG_Report.tex_normal_range_offset&gt;" range_offset_y="&lt;bpy_float[3], VATBAKER_PG_Report.tex_normal_range_offset&gt;" range_offset_z="&lt;bpy_float[3], VATBAKER_PG_Report.tex_normal_range_offset&gt;" /></Textures><Animations><Animation name="Peewee_Ground_Idle" start_frame="1" end_frame="5" frames="5" /><Animation name="Peewee_Ground_Excited" start_frame="8" end_frame="29" frames="22" /><Animation name="Peewee_Ground_Sad" start_frame="32" end_frame="56" frames="25" /><Animation name="Peewee_Ground_Trot" start_frame="59" end_frame="67" frames="9" /></Animations></BakedData>